debouncer.v
module db_fsm 
( 
output reg db,
input wire sw, 
input wire clk, reset);
// symbolic state declaration 
localparam [2: 0] zero = 3'b000, 
wait1_1 = 3'b001, 
wait1_2 = 3'b010, 
wait1_3 = 3'b011, 
one = 3'b100, 
wait0_1 = 3'b101, 
wait0_2 = 3'b110, 
wait0_3 = 3'b111; 
// number of counter bits (2"N * 2Ons = 1Oms tick) 
localparam N =5; 
// signal declaration 
reg [N-1: 1] q_reg; 
wire [N-1 : 1] q_next ; 
wire m_tick; 
reg [2:0] state_reg , state_next ; 
// body 

always @ (posedge clk or posedge reset) begin
q_reg <= q_next;
if (reset) begin  
    q_reg <= 0;
end
end
assign q_next = q_reg + 1; 
// ozrtput tick 
assign m_tick = (q_reg==0) ? 1'b1 : 1'b0; 

// state register 
always @ ( posedge clk , posedge reset) begin
if (reset) 
state_reg <= zero; 
else 
state_reg <= state_next ; 

end

always@* begin 
state_next = state_reg; // default state: the same 
db = 1'b0; // default output: 0 
case (state_reg) 
zero: 
if (sw) 
state_next = wait1_1; 
wait1_1: 
if (~sw) 
state_next = zero; 
else 
if (m_tick) 
state_next = wait1_2 ; 
wait1_2 : 
if (~sw) 
state_next = zero; 
else 
if (m_tick) 
state_next = wait1_3; 
wait1_3 : 
if (~sw) 
state_next = zero; 
else 
if (m_tick) 
state_next = one; 
one : 
begin 
db = 1'b1; 
if (~sw) 
state_next = wait0_1; 
end 
wait0_1: 
begin 
db = 1'b1; 
if (sw) 
state_next = one; 
else 
if (m_tick) 
state_next = wait0_2; 
end 
wait0_2:
begin
db = 1'b1; 
if (sw) 
state_next = one; 
else 
if (m_tick) 
state_next = wait0_3; 
end 
wait0_3 : 
begin 
db = 1'b1; 
if (sw) 
state_next = one; 
else 
if (m_tick) 
state_next = zero; 
end 
default : state_next = zero; 
endcase 
end 
endmodule

alternative_debouncer.v
module alternative_debouncer(out, in, clk, rst);

input in, clk, rst;
output reg out;

localparam [2: 0] zero = 3'b000, wait_0 = 3'b001, wait_1 = 3'b010, one = 3'b011;

// number of counter bits (2"N * 2Ons = lOms tick) 
localparam N =5; 
// signal declaration 
reg [N-1: 0] q_reg; 
wire [N-1 : 0] q_next; 
wire m_tick; 

reg [2:0] state_reg , state_next; 

always @ (posedge clk or posedge rst)  begin
    q_reg <= q_next;
    if (rst)
        q_reg <= 0;
end        
assign q_next = q_reg + 1; 
assign m_tick = (q_reg==0) ? 1'b1 : 1'b0;


always@(posedge clk, posedge rst) begin
    if (rst) 
        state_reg = zero;
    else
        state_reg = state_next;
end


always@* begin
state_next = state_reg;

case (state_reg)
    zero: begin
        out = 1'b0;
        if (in & m_tick)
            state_next = one;
        else
            state_next = state_reg;
        end
    wait_1: begin
        if (~in & m_tick)
            state_next = zero;
        end
    one: begin
        out = 1'b1;
        if (in & m_tick) state_next = state_reg;
        else begin
            state_next = wait_1;
        end
    end
    default:
        state_next = zero;
endcase
end

endmodule


module main();
reg in, clk, rst;
wire outp, out2;


alternative_debouncer d1(outp, in, clk, rst);
db_fsm f1(out2, in, clk, rst);

initial begin
clk <= 0;
rst <= 0;
in <= 0;

#10 rst <= 1;
#2 rst <= 0;
#20 in <= 1;
#80 in <= 0;

#10 in <= 1;
#2 in <= 0;
#2 in <= 1;
#4 in <= 0;
#5 in <= 1;
#30 in <= 0;
#2 in <= 1;
#1 in <= 0;
#3 in <= 1;
#2 in <= 0;

#50 $finish;
end

initial begin

forever begin
#1 clk = ~clk;
end
end

initial begin
    $dumpfile("debouncer.vcd");
    $dumpvars(0, main);
end

endmodule

debouncer.vcd
$date
	Tue Nov 26 18:53:50 2024
$end
$version
	Icarus Verilog
$end
$timescale
	1s
$end
$scope module main $end
$var wire 1 ! outp $end
$var wire 1 " out2 $end
$var reg 1 # clk $end
$var reg 1 $ in $end
$var reg 1 % rst $end
$scope module d1 $end
$var wire 1 # clk $end
$var wire 1 $ in $end
$var wire 1 % rst $end
$var wire 5 & q_next [4:0] $end
$var wire 1 ' m_tick $end
$var parameter 32 ( N $end
$var parameter 3 ) one $end
$var parameter 3 * wait_0 $end
$var parameter 3 + wait_1 $end
$var parameter 3 , zero $end
$var reg 1 ! out $end
$var reg 5 - q_reg [4:0] $end
$var reg 3 . state_next [2:0] $end
$var reg 3 / state_reg [2:0] $end
$upscope $end
$scope module f1 $end
$var wire 1 # clk $end
$var wire 1 % reset $end
$var wire 1 $ sw $end
$var wire 4 0 q_next [4:1] $end
$var wire 1 1 m_tick $end
$var parameter 32 2 N $end
$var parameter 3 3 one $end
$var parameter 3 4 wait0_1 $end
$var parameter 3 5 wait0_2 $end
$var parameter 3 6 wait0_3 $end
$var parameter 3 7 wait1_1 $end
$var parameter 3 8 wait1_2 $end
$var parameter 3 9 wait1_3 $end
$var parameter 3 : zero $end
$var reg 1 " db $end
$var reg 4 ; q_reg [4:1] $end
$var reg 3 < state_next [2:0] $end
$var reg 3 = state_reg [2:0] $end
$upscope $end
$upscope $end
$enddefinitions $end
$comment Show the parameter values. $end
$dumpall
b0 :
b11 9
b10 8
b1 7
b111 6
b110 5
b101 4
b100 3
b101 2
b0 ,
b10 +
b1 *
b11 )
b101 (
$end
#0
$dumpvars
bx =
b0 <
bx ;
x1
bx 0
bx /
b0 .
bx -
x'
bx &
0%
0$
0#
0"
x!
$end
#1
b0 =
0!
b0 /
1#
#2
0#
#3
1#
#4
0#
#5
1#
#6
0#
#7
1#
#8
0#
#9
1#
#10
11
1'
b1 0
b0 ;
b1 &
b0 -
1%
0#
#11
b1 &
b0 -
b1 0
b0 ;
1#
#12
0%
0#
#13
01
0'
b10 0
b1 ;
b10 &
b1 -
1#
#14
0#
#15
b11 &
b10 -
b11 0
b10 ;
1#
#16
0#
#17
b100 0
b11 ;
b100 &
b11 -
1#
#18
0#
#19
b101 &
b100 -
b101 0
b100 ;
1#
#20
0#
#21
b110 0
b101 ;
b110 &
b101 -
1#
#22
0#
#23
b111 &
b110 -
b111 0
b110 ;
1#
#24
0#
#25
b1000 0
b111 ;
b1000 &
b111 -
1#
#26
0#
#27
b1001 &
b1000 -
b1001 0
b1000 ;
1#
#28
0#
#29
b1010 0
b1001 ;
b1010 &
b1001 -
1#
#30
0#
#31
b1011 &
b1010 -
b1011 0
b1010 ;
1#
#32
b1 <
1$
0#
#33
b1 =
b1100 0
b1011 ;
b1100 &
b1011 -
1#
#34
0#
#35
b1101 &
b1100 -
b1101 0
b1100 ;
1#
#36
0#
#37
b1110 0
b1101 ;
b1110 &
b1101 -
1#
#38
0#
#39
b1111 &
b1110 -
b1111 0
b1110 ;
1#
#40
0#
#41
b0 0
b1111 ;
b10000 &
b1111 -
1#
#42
0#
#43
b10 <
11
b10001 &
b10000 -
b1 0
b0 ;
1#
#44
0#
#45
01
b10 =
b10 0
b1 ;
b10010 &
b10001 -
1#
#46
0#
#47
b10011 &
b10010 -
b11 0
b10 ;
1#
#48
0#
#49
b100 0
b11 ;
b10100 &
b10011 -
1#
#50
0#
#51
b10101 &
b10100 -
b101 0
b100 ;
1#
#52
0#
#53
b110 0
b101 ;
b10110 &
b10101 -
1#
#54
0#
#55
b10111 &
b10110 -
b111 0
b110 ;
1#
#56
0#
#57
b1000 0
b111 ;
b11000 &
b10111 -
1#
#58
0#
#59
b11001 &
b11000 -
b1001 0
b1000 ;
1#
#60
0#
#61
b1010 0
b1001 ;
b11010 &
b11001 -
1#
#62
0#
#63
b11011 &
b11010 -
b1011 0
b1010 ;
1#
#64
0#
#65
b1100 0
b1011 ;
b11100 &
b11011 -
1#
#66
0#
#67
b11101 &
b11100 -
b1101 0
b1100 ;
1#
#68
0#
#69
b1110 0
b1101 ;
b11110 &
b11101 -
1#
#70
0#
#71
b11111 &
b11110 -
b1111 0
b1110 ;
1#
#72
0#
#73
b0 0
b1111 ;
b0 &
b11111 -
1#
#74
0#
#75
b11 .
b11 <
1'
11
b1 &
b0 -
b1 0
b0 ;
1#
#76
0#
#77
b10 .
01
0'
b11 =
b10 0
b1 ;
b10 &
b1 -
1!
b11 /
1#
#78
0#
#79
b11 &
b10 -
b11 0
b10 ;
b10 /
1#
#80
0#
#81
b100 0
b11 ;
b100 &
b11 -
1#
#82
0#
#83
b101 &
b100 -
b101 0
b100 ;
1#
#84
0#
#85
b110 0
b101 ;
b110 &
b101 -
1#
#86
0#
#87
b111 &
b110 -
b111 0
b110 ;
1#
#88
0#
#89
b1000 0
b111 ;
b1000 &
b111 -
1#
#90
0#
#91
b1001 &
b1000 -
b1001 0
b1000 ;
1#
#92
0#
#93
b1010 0
b1001 ;
b1010 &
b1001 -
1#
#94
0#
#95
b1011 &
b1010 -
b1011 0
b1010 ;
1#
#96
0#
#97
b1100 0
b1011 ;
b1100 &
b1011 -
1#
#98
0#
#99
b1101 &
b1100 -
b1101 0
b1100 ;
1#
#100
0#
#101
b1110 0
b1101 ;
b1110 &
b1101 -
1#
#102
0#
#103
b1111 &
b1110 -
b1111 0
b1110 ;
1#
#104
0#
#105
b0 0
b1111 ;
b10000 &
b1111 -
1#
#106
0#
#107
b100 <
11
b10001 &
b10000 -
b1 0
b0 ;
1#
#108
0#
#109
1"
01
b100 =
b10 0
b1 ;
b10010 &
b10001 -
1#
#110
0#
#111
b10011 &
b10010 -
b11 0
b10 ;
1#
#112
b101 <
1"
0$
0#
#113
1"
b101 =
b100 0
b11 ;
b10100 &
b10011 -
1#
#114
0#
#115
b10101 &
b10100 -
b101 0
b100 ;
1#
#116
0#
#117
b110 0
b101 ;
b10110 &
b10101 -
1#
#118
0#
#119
b10111 &
b10110 -
b111 0
b110 ;
1#
#120
0#
#121
b1000 0
b111 ;
b11000 &
b10111 -
1#
#122
b100 <
1"
1$
0#
#123
1"
b11001 &
b11000 -
b1001 0
b1000 ;
b100 =
1#
#124
b101 <
1"
0$
0#
#125
1"
b101 =
b1010 0
b1001 ;
b11010 &
b11001 -
1#
#126
b100 <
1"
1$
0#
#127
1"
b11011 &
b11010 -
b1011 0
b1010 ;
b100 =
1#
#128
0#
#129
b1100 0
b1011 ;
b11100 &
b11011 -
1#
#130
b101 <
1"
0$
0#
#131
1"
b11101 &
b11100 -
b1101 0
b1100 ;
b101 =
1#
#132
0#
#133
b1110 0
b1101 ;
b11110 &
b11101 -
1#
#134
0#
#135
b100 <
1"
b11111 &
b11110 -
b1111 0
b1110 ;
1$
1#
#136
0#
#137
1"
b100 =
b0 0
b1111 ;
b0 &
b11111 -
1#
#138
0#
#139
1"
1'
11
b1 &
b0 -
b1 0
b0 ;
1#
#140
0#
#141
1"
01
0'
b10 0
b1 ;
b10 &
b1 -
1#
#142
0#
#143
b11 &
b10 -
b11 0
b10 ;
1#
#144
0#
#145
b100 0
b11 ;
b100 &
b11 -
1#
#146
0#
#147
b101 &
b100 -
b101 0
b100 ;
1#
#148
0#
#149
b110 0
b101 ;
b110 &
b101 -
1#
#150
0#
#151
b111 &
b110 -
b111 0
b110 ;
1#
#152
0#
#153
b1000 0
b111 ;
b1000 &
b111 -
1#
#154
0#
#155
b1001 &
b1000 -
b1001 0
b1000 ;
1#
#156
0#
#157
b1010 0
b1001 ;
b1010 &
b1001 -
1#
#158
0#
#159
b1011 &
b1010 -
b1011 0
b1010 ;
1#
#160
0#
#161
b1100 0
b1011 ;
b1100 &
b1011 -
1#
#162
0#
#163
b1101 &
b1100 -
b1101 0
b1100 ;
1#
#164
0#
#165
b101 <
1"
b1110 0
b1101 ;
b1110 &
b1101 -
0$
1#
#166
0#
#167
b100 <
1"
b1111 &
b1110 -
b1111 0
b1110 ;
b101 =
1$
1#
#168
1"
b101 <
0$
0#
#169
b0 0
b1111 ;
b10000 &
b1111 -
1#
#170
0#
#171
11
b100 <
1"
b10001 &
b10000 -
b1 0
b0 ;
1$
1#
#172
0#
#173
01
b101 <
1"
b100 =
b10 0
b1 ;
b10010 &
b10001 -
0$
1#
#174
0#
#175
1"
b10011 &
b10010 -
b11 0
b10 ;
b101 =
1#
#176
0#
#177
b100 0
b11 ;
b10100 &
b10011 -
1#
#178
0#
#179
b10101 &
b10100 -
b101 0
b100 ;
1#
#180
0#
#181
b110 0
b101 ;
b10110 &
b10101 -
1#
#182
0#
#183
b10111 &
b10110 -
b111 0
b110 ;
1#
#184
0#
#185
b1000 0
b111 ;
b11000 &
b10111 -
1#
#186
0#
#187
b11001 &
b11000 -
b1001 0
b1000 ;
1#
#188
0#
#189
b1010 0
b1001 ;
b11010 &
b11001 -
1#
#190
0#
#191
b11011 &
b11010 -
b1011 0
b1010 ;
1#
#192
0#
#193
b1100 0
b1011 ;
b11100 &
b11011 -
1#
#194
0#
#195
b11101 &
b11100 -
b1101 0
b1100 ;
1#
#196
0#
#197
b1110 0
b1101 ;
b11110 &
b11101 -
1#
#198
0#
#199
b11111 &
b11110 -
b1111 0
b1110 ;
1#
#200
0#
#201
b0 0
b1111 ;
b0 &
b11111 -
1#
#202
0#
#203
b0 .
b110 <
1"
1'
11
b1 &
b0 -
b1 0
b0 ;
1#
#204
0#
#205
1"
01
0'
b110 =
b10 0
b1 ;
b10 &
b1 -
0!
b0 /
1#
#206
0#
#207
b11 &
b10 -
b11 0
b10 ;
1#
#208
0#
#209
b100 0
b11 ;
b100 &
b11 -
1#
#210
0#
#211
b101 &
b100 -
b101 0
b100 ;
1#
#212
0#
#213
b110 0
b101 ;
b110 &
b101 -
1#
#214
0#
#215
b111 &
b110 -
b111 0
b110 ;
1#
#216
0#
#217
b1000 0
b111 ;
b1000 &
b111 -
1#
#218
0#
#219
b1001 &
b1000 -
b1001 0
b1000 ;
1#
#220
0#
#221
b1010 0
b1001 ;
b1010 &
b1001 -
1#
#222
0#
#223
b1011 &
b1010 -
b1011 0
b1010 ;
1#
