occupancy_counter.v
module occupancy_counter(enter, exit, a, b, clk, rst);

input a, b, clk, rst;
output reg enter, exit;

localparam [2: 0] NO_OBJECT = 3'b000, ENTRY = 3'b001, MOVING = 3'b010, EXIT = 3'b011;

reg [2: 0] current_state, next_state;

always@(posedge clk, posedge rst) begin
  if (rst)
    current_state = NO_OBJECT;
  else
    current_state = next_state;
end

always@* begin
next_state = current_state;
enter = 1'b0;
exit = 1'b0;
    case(current_state)
        NO_OBJECT: begin
            if (a & ~b)
                next_state = ENTRY;
            if (b & ~a)
                next_state = EXIT;
            end
        ENTRY: begin
            if (a & b) begin
                enter <= 1'b1;
                next_state = MOVING;
            end
            if (~a) begin
                next_state = NO_OBJECT;
            end
        end
        MOVING: begin
            if (a & ~b)
                next_state = EXIT;
            else if (~a & b)
                next_state = ENTRY;
        end
        EXIT: begin
            if (~b) begin
                next_state = NO_OBJECT;
            end
            else if (a & b) begin
                exit <= 1'b1;
                next_state = MOVING;
            end
        end
endcase
end

endmodule


module car_counter#(parameter size=4)(count, inc, dec, rst);
input inc, dec, rst;
output reg [size - 1: 0] count;

always@(rst, inc, dec) begin
    if (rst)
        count <= 0;
    if (inc)
        count <= count + 1;
    else if (dec)
        count <= count - 1;
end

endmodule

module main();

reg a, b, clk, rst;
wire entry, exit;
wire [3: 0] car_count;
occupancy_counter oc(entry, exit, a, b, clk ,rst);
car_counter cc(car_count, entry, exit, rst);

initial begin
rst <= 1'b0;
clk <= 1'b0;
a <= 1'b0;
b <= 1'b0;

// testing entry
#5 rst <= 1'b1;
#5 rst <= 1'b0;
#10 a <= 1'b1;
#10 b <= 1'b1;
#10 a <= 1'b0;
#10 b <= 1'b0;

// testing exit
#10 b <= 1'b1;
#10 a <= 1'b1;
#10 b <= 1'b0;
#10 a <= 1'b0;

//
#10 a <= 1'b1;
#10 b <= 1'b1;
#10 a <= 1'b0;

#40 $finish;
end

initial begin
    forever
        #2 clk = ~clk;
end

initial begin
    $dumpfile("occupancy.vcd");
    $dumpvars(0, main);
end

endmodule

occupancy.vcd
$date
	Tue Nov 26 21:43:44 2024
$end
$version
	Icarus Verilog
$end
$timescale
	1s
$end
$scope module main $end
$var wire 1 ! exit $end
$var wire 1 " entry $end
$var wire 4 # car_count [3:0] $end
$var reg 1 $ a $end
$var reg 1 % b $end
$var reg 1 & clk $end
$var reg 1 ' rst $end
$scope module cc $end
$var wire 1 ' rst $end
$var wire 1 " inc $end
$var wire 1 ! dec $end
$var parameter 32 ( size $end
$var reg 4 ) count [3:0] $end
$upscope $end
$scope module oc $end
$var wire 1 $ a $end
$var wire 1 % b $end
$var wire 1 & clk $end
$var wire 1 ' rst $end
$var parameter 3 * ENTRY $end
$var parameter 3 + EXIT $end
$var parameter 3 , MOVING $end
$var parameter 3 - NO_OBJECT $end
$var reg 3 . current_state [2:0] $end
$var reg 1 " enter $end
$var reg 1 ! exit $end
$var reg 3 / next_state [2:0] $end
$upscope $end
$upscope $end
$enddefinitions $end
$comment Show the parameter values. $end
$dumpall
b0 -
b10 ,
b11 +
b1 *
b100 (
$end
#0
$dumpvars
bx /
bx .
bx )
0'
0&
0%
0$
bx #
0"
0!
$end
#2
1&
#4
0&
#5
b0 #
b0 )
b0 /
b0 .
1'
#6
1&
#8
0&
#10
0'
1&
#12
0&
#14
1&
#16
0&
#18
1&
#20
b1 /
1$
0&
#22
b1 .
1&
#24
0&
#26
1&
#28
0&
#30
b1 #
b1 )
1"
b10 /
1%
1&
#32
0&
#34
0"
b10 .
1&
#36
0&
#38
1&
#40
b1 /
0$
0&
#42
b0 /
b1 .
1&
#44
0&
#46
b11 /
b0 .
1&
#48
0&
#50
b0 /
0%
b11 .
1&
#52
0&
#54
b0 .
1&
#56
0&
#58
1&
#60
b11 /
1%
0&
#62
b11 .
1&
#64
0&
#66
1&
#68
0&
#70
b0 #
b0 )
1!
b10 /
1$
1&
#72
0&
#74
0!
b10 .
1&
#76
0&
#78
1&
#80
b11 /
0%
0&
#82
b0 /
b11 .
1&
#84
0&
#86
b1 /
b0 .
1&
#88
0&
#90
b0 /
0$
b1 .
1&
#92
0&
#94
b0 .
1&
#96
0&
#98
1&
#100
b1 /
1$
0&
#102
b1 .
1&
#104
0&
#106
1&
#108
0&
#110
b1 #
b1 )
1"
b10 /
1%
1&
#112
0&
#114
0"
b10 .
1&
#116
0&
#118
1&
#120
b1 /
0$
0&
#122
b0 /
b1 .
1&
#124
0&
#126
b11 /
b0 .
1&
#128
0&
#130
b11 .
1&
